{
  "_class": "symbolInstance",
  "do_objectID": "9789DFB6-0BF8-4AA7-8560-3C4BD9FC9F11",
  "exportOptions": {
    "_class": "exportOptions",
    "do_objectID": "D94DACF2-596D-4655-8679-A7B3A9ACA1EE",
    "exportFormats": [
    ],
    "includedLayerIds": [
    ],
    "layerOptions": 0,
    "shouldTrim": false
  },
  "frame": {
    "_class": "rect",
    "constrainProportions": false,
    "do_objectID": "C4222562-DA8C-44F4-BB98-16EF6F94736E",
    "height": 16,
    "width": 88,
    "x": 205,
    "y": 400
  },
  "horizontalSpacing": 0,
  "isFlippedHorizontal": false,
  "isFlippedVertical": false,
  "isLocked": false,
  "isVisible": true,
  "layerListExpandedType": 0,
  "name": "text/info copy 10",
  "nameIsFixed": false,
  "overrideValues": [
    {
      "_class": "overrideValue",
      "do_objectID": "91886D81-D9BE-4794-95C5-CECF5C1E7FC7",
      "overrideName": "A52D9AE4-52A6-4695-8775-8E63A348C1B1_stringValue",
      "value": "Wireframes"
    }
  ],
  "resizingConstraint": 63,
  "resizingType": 0,
  "rotation": 0,
  "scale": 1,
  "shouldBreakMaskChain": false,
  "style": {
    "_class": "style",
    "do_objectID": "28682377-6A1D-43DE-A34F-61A16B369653",
    "endDecorationType": 0,
    "miterLimit": 10,
    "startDecorationType": 0
  },
  "symbolID": "84C390E5-C8DC-4DA4-8C6A-D589051EB034",
  "verticalSpacing": 0
}